LICENSE.txt
README.md
setup.cfg
setup.py
src/__init__.py
src/tokotime/__init__.py
src/tokotime.egg-info/PKG-INFO
src/tokotime.egg-info/SOURCES.txt
src/tokotime.egg-info/dependency_links.txt
src/tokotime.egg-info/requires.txt
src/tokotime.egg-info/top_level.txt
src/tokotime/data_utils/__init__.py
src/tokotime/data_utils/utils.py
src/tokotime/experiment_design/__init__.py
src/tokotime/experiment_design/random_sampler.py
src/tokotime/features_eng/__init__.py
src/tokotime/features_eng/base_eng.py
src/tokotime/hp_tune/bayes_hp_tuner.py
src/tokotime/point_forecasts/__init__.py
src/tokotime/point_forecasts/evaluation_metrics.py
src/tokotime/point_forecasts/evaluator.py
src/tokotime/point_forecasts/misc.py
src/tokotime/point_forecasts/model_mapping.py
src/tokotime/point_forecasts/model_runner.py
src/tokotime/point_forecasts/model_wrappers.py
src/tokotime/point_forecasts/ts_class.py
src/tokotime/point_forecasts/validation.py
src/tokotime/preprocess_utils/__init__.py
src/tokotime/preprocess_utils/preprocess_components.py
src/tokotime/preprocess_utils/preprocessors.py
src/tokotime/probabilistic_forecasts/__init__.py
src/tokotime/probabilistic_forecasts/evaluation_metrics.py